xyzstyle-0.2.0.dist-info/METADATA
xyzstyle-0.2.0.dist-info/WHEEL
xyzstyle-0.2.0.dist-info/entry_points.txt
xyzstyle-0.2.0.dist-info/licenses/LICENSE
xyzstyle/__init__.py
xyzstyle/set_theme.py
xyzstyle/theme/xyzstyle/layout.html
xyzstyle/theme/xyzstyle/static/css/custom.css
xyzstyle/theme/xyzstyle/static/css/tippy.css
xyzstyle/theme/xyzstyle/static/css/try_examples.css
xyzstyle/theme/xyzstyle/static/js/custom-icon.js
xyzstyle/theme/xyzstyle/theme.toml
xyzstyle-0.2.0.dist-info/RECORD
