Metadata-Version: 2.1
Name: xyzstyle
Version: 0.2.0
Summary: xyzstyle 主题 - 基于 sphinx-book-theme 的现代 Sphinx 文档主题
Author-Email: xinetzone <735613050@qq.com>
Maintainer-Email: xinetzone <735613050@qq.com>
License:                                  Apache License
Project-URL: Repository, https://github.com/xinetzone/xyzstyle
Project-URL: Documentation, https://xyzstyle.readthedocs.io/
Project-URL: Issues, https://github.com/xinetzone/xyzstyle/issues
Requires-Python: >=3.12
Requires-Dist: sphinx-book-theme
Provides-Extra: doc
Requires-Dist: sphinx>=8.0.0; extra == "doc"
Requires-Dist: ablog; extra == "doc"
Requires-Dist: ipywidgets; extra == "doc"
Requires-Dist: numpy; extra == "doc"
Requires-Dist: matplotlib; extra == "doc"
Requires-Dist: sphinx-comments; extra == "doc"
Requires-Dist: myst-nb; extra == "doc"
Requires-Dist: nbclient; extra == "doc"
Requires-Dist: pandas; extra == "doc"
Requires-Dist: plotly; extra == "doc"
Requires-Dist: sphinx-design; extra == "doc"
Requires-Dist: sphinx-examples; extra == "doc"
Requires-Dist: sphinx-copybutton; extra == "doc"
Requires-Dist: sphinx-contributors; extra == "doc"
Requires-Dist: sphinx-thebe; extra == "doc"
Requires-Dist: sphinxcontrib-bibtex; extra == "doc"
Requires-Dist: sphinxext-opengraph; extra == "doc"
Requires-Dist: sphinx-sitemap; extra == "doc"
Requires-Dist: sphinx-autoapi>=3.4; extra == "doc"
Requires-Dist: graphviz; extra == "doc"
Requires-Dist: sphinx-tippy; extra == "doc"
Provides-Extra: dev
Requires-Dist: invoke; extra == "dev"
Requires-Dist: taolib; extra == "dev"
